business_logic/__init__.py
business_logic/admin.py
business_logic/apps.py
business_logic/config.py
business_logic/exceptions.py
business_logic/fields.py
business_logic/signals.py
business_logic/urls.py
business_logic/utils.py
business_logic/validators.py
business_logic/blockly/__init__.py
business_logic/blockly/build.py
business_logic/blockly/create.py
business_logic/blockly/data.py
business_logic/blockly/exceptions.py
business_logic/blockly/parse.py
business_logic/locale/ru/LC_MESSAGES/django.mo
business_logic/locale/ru/LC_MESSAGES/django.po
business_logic/migrations/0001_initial.py
business_logic/migrations/__init__.py
business_logic/models/__init__.py
business_logic/models/assignment.py
business_logic/models/constant.py
business_logic/models/context.py
business_logic/models/foreach.py
business_logic/models/frame.py
business_logic/models/function.py
business_logic/models/ifstatement.py
business_logic/models/log.py
business_logic/models/node.py
business_logic/models/operator_.py
business_logic/models/program.py
business_logic/models/reference.py
business_logic/models/stop.py
business_logic/models/table.py
business_logic/models/types_.py
business_logic/models/variable.py
business_logic/rest/__init__.py
business_logic/rest/serializers.py
business_logic/rest/urls.py
business_logic/rest/views.py
business_logic/static/business_logic/index.html
business_logic/static/business_logic/main.bundle.js
business_logic/static/business_logic/main.bundle.map
business_logic/static/business_logic/polyfills.bundle.js
business_logic/static/business_logic/polyfills.bundle.map
business_logic/static/business_logic/vendor.bundle.js
business_logic/static/business_logic/vendor.bundle.map
business_logic/static/business_logic/blockly/1x1.gif
business_logic/static/business_logic/blockly/accessible.css
business_logic/static/business_logic/blockly/click.mp3
business_logic/static/business_logic/blockly/click.ogg
business_logic/static/business_logic/blockly/click.wav
django_business_logic-0.6.0.dist-info/LICENSE.txt
django_business_logic-0.6.0.dist-info/METADATA
django_business_logic-0.6.0.dist-info/WHEEL
django_business_logic-0.6.0.dist-info/top_level.txt
django_business_logic-0.6.0.dist-info/RECORD
