Metadata-Version: 2.1
Name: django-business-logic
Version: 0.6.0
Summary: Visual DSL framework for django
Home-page: https://github.com/dgk/django-business-logic
Download-URL: https://github.com/dgk/django-business-logic/archive/0.6.0.tar.gz
Author: Dmitry Kuksinsky
Author-email: dgk@dgk.su
License: MIT
Keywords: django
Classifier: Development Status :: 3 - Alpha
Classifier: Environment :: Web Environment
Classifier: Intended Audience :: Developers
Classifier: License :: OSI Approved :: MIT License
Classifier: Operating System :: OS Independent
Classifier: Programming Language :: Python :: 3
Classifier: Programming Language :: Python :: 3.8
Classifier: Programming Language :: Python :: 3.9
Classifier: Programming Language :: Python :: 3.10
Classifier: Programming Language :: Python :: 3.11
Classifier: Topic :: Internet :: WWW/HTTP
Classifier: Topic :: Internet :: WWW/HTTP :: Dynamic Content
Classifier: Framework :: Django
Classifier: Framework :: Django :: 3.2
Classifier: Framework :: Django :: 4.0
Classifier: Framework :: Django :: 4.1
Classifier: Framework :: Django :: 4.2
License-File: LICENSE.txt
Requires-Dist: Markdown <=3.4.4
Requires-Dist: django-ace-overlay ==0.8.0
Requires-Dist: django-admin-sortable2 >=1.0.4
Requires-Dist: django-filter ==23.2
Requires-Dist: django-nested-admin ==4.0.2
Requires-Dist: django-polymorphic ==3.1.0
Requires-Dist: django-treebeard ==4.7
Requires-Dist: djangorestframework >=3.14.0
Requires-Dist: lxml <5.0
